MANIFEST.in
README.md
setup.py
sovrin/__init__.py
sovrin/__metadata__.py
sovrin/domain_transactions_builder_genesis
sovrin/domain_transactions_live_genesis
sovrin/domain_transactions_local_genesis
sovrin/domain_transactions_sandbox_genesis
sovrin/manifest.txt
sovrin/pool_transactions_builder_genesis
sovrin/pool_transactions_live_genesis
sovrin/pool_transactions_local_genesis
sovrin/pool_transactions_sandbox_genesis
sovrin/pool_transactions_training_genesis
sovrin_dev.egg-info/PKG-INFO
sovrin_dev.egg-info/SOURCES.txt
sovrin_dev.egg-info/dependency_links.txt
sovrin_dev.egg-info/requires.txt
sovrin_dev.egg-info/top_level.txt