Metadata-Version: 1.0
Name: sovrin-dev
Version: 1.1.119
Summary: Sovrin node
Home-page: https://github.com/sovrin-foundation/sovrin
Author: Sovrin Foundation.
Author-email: dev@evernym.us
License: Apache 2.0
Keywords: Sovrin Genesis Transactions
Platform: UNKNOWN
